CHANGELOG.rst
MANIFEST.in
README.rst
setup.py
syslogging/__init__.py
syslogging.egg-info/PKG-INFO
syslogging.egg-info/SOURCES.txt
syslogging.egg-info/dependency_links.txt
syslogging.egg-info/top_level.txt
syslogging/tests/__init__.py
syslogging/tests/test_sysloghandler.py