Metadata-Version: 1.1
Name: syslogging
Version: 0.1.1
Summary: A logging Handler that logs to syslog using syslog(3)
Home-page: https://github.com/kampka/syslogging
Author: Christian Kampka
Author-email: christian@kampka.net
License: BSD-3
Platform: UNKNOWN
Classifier: Development Status :: 5 - Production/Stable
Classifier: Intended Audience :: Developers
Classifier: License :: OSI Approved :: BSD License
Classifier: Operating System :: OS Independent
Classifier: Programming Language :: Python
Classifier: Programming Language :: Python :: 3
Classifier: Topic :: Software Development
Classifier: Topic :: System :: Logging
